reader/__init__.py
reader/__main__.py
reader/config.toml
reader/feed.py
reader/viewer.py
paul_realpython_reader-1.2.1.dist-info/LICENSE
paul_realpython_reader-1.2.1.dist-info/METADATA
paul_realpython_reader-1.2.1.dist-info/WHEEL
paul_realpython_reader-1.2.1.dist-info/entry_points.txt
paul_realpython_reader-1.2.1.dist-info/top_level.txt
paul_realpython_reader-1.2.1.dist-info/RECORD
